rstar-0.1.0.dist-info/METADATA
rstar-0.1.0.dist-info/WHEEL
rstar-0.1.0.dist-info/license_files/LICENSE
rstar/__init__.py
rstar/rstar.cp38-win_amd64.pyd
rstar-0.1.0.dist-info/RECORD
