Metadata-Version: 2.1
Name: rstar
Version: 0.1.0
Requires-Dist: numpy >= 1.16.0
Requires-Dist: typing_extensions >= 4.0.0; python_version < '3.10'
Requires-Dist: pyarrow>=4.0.*; extra == 'pandas'
Requires-Dist: pandas; extra == 'pandas'
Requires-Dist: pyarrow>=4.0.*; extra == 'pyarrow'
Provides-Extra: pandas
Provides-Extra: pyarrow
License-File: LICENSE
Requires-Python: >=3.7
